hlsdl/__init__.py
hlsdl/__main__.py
hlsdl/cli.py
hlsdl/cmdargs.py
hlsdl/daemon.py
hlsdl/downloader.py
hlsdl/extractor.py
hlsdl/log.py
hlsdl/version.py
hlsdl/extractors/__init__.py
hlsdl/extractors/base.py
hlsdl/extractors/metaitem.py
hlsdl/extractors/dash/__init__.py
hlsdl/extractors/dash/funcs.py
hlsdl/extractors/dash/handler.py
hlsdl/extractors/dash/key.py
hlsdl/extractors/dash/mpd.py
hlsdl/extractors/dash/mpditem.py
hlsdl/extractors/dash/parser.py
hlsdl/extractors/dash/segment.py
hlsdl/extractors/dash/stream.py
hlsdl/extractors/dash/childs/__init__.py
hlsdl/extractors/dash/childs/adaptationset.py
hlsdl/extractors/dash/childs/baseurl.py
hlsdl/extractors/dash/childs/cencpssh.py
hlsdl/extractors/dash/childs/contentprotection.py
hlsdl/extractors/dash/childs/initialization.py
hlsdl/extractors/dash/childs/location.py
hlsdl/extractors/dash/childs/period.py
hlsdl/extractors/dash/childs/representation.py
hlsdl/extractors/dash/childs/role.py
hlsdl/extractors/dash/childs/s.py
hlsdl/extractors/dash/childs/segmentbase.py
hlsdl/extractors/dash/childs/segmentlist.py
hlsdl/extractors/dash/childs/segmenttemplate.py
hlsdl/extractors/dash/childs/segmenttimeline.py
hlsdl/extractors/dash/childs/segmenturl.py
hlsdl/extractors/dash/maps/__init__.py
hlsdl/extractors/dash/maps/audiomap.py
hlsdl/extractors/hls/parser.py
hlsdl/extractors/hls/segment.py
hlsdl/extractors/hls/stream.py
hlsdl/extractors/hls/ext/x.py
hlsdl/extractors/hls/ext/xdaterange.py
hlsdl/extractors/hls/ext/xkey.py
hlsdl/extractors/hls/ext/xmedia.py
hlsdl/extractors/hls/ext/xprivinf.py
hlsdl/extractors/hls/ext/xprogram_date_time.py
hlsdl/extractors/hls/ext/xstream_inf.py
hlsdl/extractors/mss/box_util.py
hlsdl/extractors/mss/handler.py
hlsdl/extractors/mss/ism.py
hlsdl/extractors/mss/ismitem.py
hlsdl/extractors/mss/key.py
hlsdl/extractors/mss/parser.py
hlsdl/extractors/mss/segment.py
hlsdl/extractors/mss/stream.py
hlsdl/extractors/mss/childs/__init__.py
hlsdl/extractors/mss/childs/c.py
hlsdl-1.0.1.dist-info/LICENSE
hlsdl-1.0.1.dist-info/METADATA
hlsdl-1.0.1.dist-info/WHEEL
hlsdl-1.0.1.dist-info/top_level.txt
hlsdl-1.0.1.dist-info/RECORD
