Metadata-Version: 2.1
Name: hlsdl
Version: 1.0.1
License-File: LICENSE
Requires-Dist: aiohttp
Requires-Dist: aiohttp-socks
Requires-Dist: argparse
Requires-Dist: pycryptodome
